zerodb/__init__.py
zerodb/__init__.pyc
zerodb/api.py
zerodb/api.pyc
zerodb/db.py
zerodb/db.pyc
zerodb/intid.py
zerodb/intid.pyc
zerodb/query.py
zerodb/query.pyc
zerodb/testing.py
zerodb/testing.pyc
zerodb/catalog/__init__.py
zerodb/catalog/__init__.pyc
zerodb/catalog/query.py
zerodb/catalog/query.pyc
zerodb/catalog/query_json.py
zerodb/catalog/query_json.pyc
zerodb/catalog/indexes/__init__.py
zerodb/catalog/indexes/__init__.pyc
zerodb/catalog/indexes/common.py
zerodb/catalog/indexes/common.pyc
zerodb/catalog/indexes/facet.py
zerodb/catalog/indexes/facet.pyc
zerodb/catalog/indexes/field.py
zerodb/catalog/indexes/field.pyc
zerodb/catalog/indexes/keyword.py
zerodb/catalog/indexes/keyword.pyc
zerodb/catalog/indexes/path.py
zerodb/catalog/indexes/path.pyc
zerodb/catalog/indexes/path2.py
zerodb/catalog/indexes/path2.pyc
zerodb/catalog/indexes/pwid.py
zerodb/catalog/indexes/pwid.pyc
zerodb/catalog/indexes/text.py
zerodb/catalog/indexes/text.pyc
zerodb/catalog/indexes/text_lexicon.py
zerodb/catalog/indexes/text_lexicon.pyc
zerodb/catalog/indexes/text_lucene.py
zerodb/catalog/indexes/text_lucene.pyc
zerodb/catalog/indexes/text_okapi.py
zerodb/catalog/indexes/text_okapi.pyc
zerodb/collective/__init__.py
zerodb/collective/__init__.pyc
zerodb/collective/indexing/__init__.py
zerodb/collective/indexing/__init__.pyc
zerodb/collective/indexing/config.py
zerodb/collective/indexing/config.pyc
zerodb/collective/indexing/indexer.py
zerodb/collective/indexing/indexer.pyc
zerodb/collective/indexing/interfaces.py
zerodb/collective/indexing/interfaces.pyc
zerodb/collective/indexing/queue.py
zerodb/collective/indexing/queue.pyc
zerodb/collective/indexing/subscribers.py
zerodb/collective/indexing/subscribers.pyc
zerodb/collective/indexing/transactions.py
zerodb/collective/indexing/transactions.pyc
zerodb/crypto/__init__.py
zerodb/crypto/__init__.pyc
zerodb/crypto/ecc.py
zerodb/crypto/ecc.pyc
zerodb/crypto/exceptions.py
zerodb-0.98.0.dist-info/DESCRIPTION.rst
zerodb-0.98.0.dist-info/METADATA
zerodb-0.98.0.dist-info/RECORD
zerodb-0.98.0.dist-info/WHEEL
zerodb-0.98.0.dist-info/metadata.json
zerodb-0.98.0.dist-info/top_level.txt
