Metadata-Version: 2.0
Name: zerodb
Version: 0.98.0
Summary: End-to-end encrypted database
Home-page: http://zerodb.io
Author: ZeroDB Inc.
Author-email: michael@zerodb.io
License: AGPLv3
Platform: UNKNOWN
Requires-Dist: BTrees
Requires-Dist: ZEO (>=4.0.0)
Requires-Dist: ZODB (>=4.0.0)
Requires-Dist: aes256gcm-nacl
Requires-Dist: cachetools
Requires-Dist: ecdsa (>=0.10)
Requires-Dist: flask (>=0.10)
Requires-Dist: flask-cors
Requires-Dist: jsonpickle
Requires-Dist: pycryptodome
Requires-Dist: requests (>=2.0)
Requires-Dist: scrypt
Requires-Dist: six (>=1.7.0)
Requires-Dist: zc.zlibstorage
Requires-Dist: zerodbext.catalog (==0.8.4)
Requires-Dist: zodbpickle
Requires-Dist: zope.component (>=4.0.0)
Requires-Dist: zope.event (>=4.0.0)
Requires-Dist: zope.index (>=4.0.0)
Requires-Dist: zope.lifecycleevent (>=4.0.0)
Provides-Extra: testing
Requires-Dist: coverage; extra == 'testing'
Requires-Dist: mock; extra == 'testing'
Requires-Dist: path.py; extra == 'testing'
Requires-Dist: pdbpp; extra == 'testing'
Requires-Dist: pytest; extra == 'testing'
Requires-Dist: pytest-cov; extra == 'testing'
Requires-Dist: wheel; extra == 'testing'
